wz_weather_plot/__about__.py
wz_weather_plot/__init__.py
wz_weather_plot/_plot_images.py
wz_weather_plot/plot.py
wz_weather_plot/static/chn/chinaGJ.json
wz_weather_plot/static/chn/chn_city.geojson
wz_weather_plot/static/chn/chn_cnty.geojson
wz_weather_plot/static/chn/chn_province.geojson
wz_weather_plot/static/chn/chn_province.shx
wz_weather_plot/static/fonts/HELVETI1.TTF
wz_weather_plot/static/fonts/msyh.ttc
wz_weather_plot/static/fonts/msyhbd.ttc
wz_weather_plot/static/fonts/msyhl.ttc
wz_weather_plot/static/fonts/simkai.ttf
wz_weather_plot/static/fonts/simsun.ttc
wz_weather_plot-0.0.8.dist-info/METADATA
wz_weather_plot-0.0.8.dist-info/WHEEL
wz_weather_plot-0.0.8.dist-info/licenses/LICENSE.txt
wz_weather_plot-0.0.8.dist-info/RECORD
