Metadata-Version: 2.3
Name: wz-weather-plot
Version: 0.0.8
Summary: 用来绘制地图数据
Project-URL: Documentation, https://github.com/yjw/wz-weather-plot#readme
Project-URL: Issues, https://github.com/yjw/wz-weather-plot/issues
Project-URL: Source, https://github.com/yjw/wz-weather-plot
Author-email: yjw <1633998687@qq.com>
License-Expression: MIT
License-File: LICENSE.txt
Classifier: Development Status :: 4 - Beta
Classifier: Programming Language :: Python :: 3.11
Requires-Python: >=3.11
Requires-Dist: cartopy>=0.20.2
Requires-Dist: chardet>=4.0.0
Requires-Dist: geopandas>=1.0.1
Requires-Dist: loguru>=0.7.2
Requires-Dist: matplotlib-inline>=0.1.7
Requires-Dist: matplotlib>=3.9.1
Requires-Dist: metpy>=1.6.3
Requires-Dist: netcdf4>=1.7.1
Requires-Dist: numpy>=1.22.3
Requires-Dist: pandas>=1.4.2
Requires-Dist: pygrib>=2.1.6
Requires-Dist: scipy>=1.14.1
Requires-Dist: xarray>=2024.7.0
